<annotation>
	<folder>Esam</folder>
	<filename>hard_hat_workers4694.png</filename>
	<path>F:\HardHat_images\Esam\hard_hat_workers4694.png</path>
	<source>
		<database>Unknown</database>
	</source>
	<size>
		<width>416</width>
		<height>415</height>
		<depth>3</depth>
	</size>
	<segmented>0</segmented>
	<object>
		<name>NV</name>
		<pose>Unspecified</pose>
		<truncated>0</truncated>
		<difficult>0</difficult>
		<bndbox>
			<xmin>109</xmin>
			<ymin>203</ymin>
			<xmax>311</xmax>
			<ymax>364</ymax>
		</bndbox>
	</object>
	<object>
		<name>NG</name>
		<pose>Unspecified</pose>
		<truncated>0</truncated>
		<difficult>0</difficult>
		<bndbox>
			<xmin>169</xmin>
			<ymin>134</ymin>
			<xmax>250</xmax>
			<ymax>166</ymax>
		</bndbox>
	</object>
	<object>
		<name>H</name>
		<pose>Unspecified</pose>
		<truncated>0</truncated>
		<difficult>0</difficult>
		<bndbox>
			<xmin>161</xmin>
			<ymin>95</ymin>
			<xmax>253</xmax>
			<ymax>202</ymax>
		</bndbox>
	</object>
</annotation>
