<annotation>
	<folder>Ahmad</folder>
	<filename>hard_hat_workers1434.png</filename>
	<path>F:\HardHat_images\Ahmad\hard_hat_workers1434.png</path>
	<source>
		<database>Unknown</database>
	</source>
	<size>
		<width>416</width>
		<height>415</height>
		<depth>3</depth>
	</size>
	<segmented>0</segmented>
	<object>
		<name>B</name>
		<pose>Unspecified</pose>
		<truncated>0</truncated>
		<difficult>0</difficult>
		<bndbox>
			<xmin>222</xmin>
			<ymin>215</ymin>
			<xmax>231</xmax>
			<ymax>221</ymax>
		</bndbox>
	</object>
	<object>
		<name>H</name>
		<pose>Unspecified</pose>
		<truncated>0</truncated>
		<difficult>0</difficult>
		<bndbox>
			<xmin>219</xmin>
			<ymin>172</ymin>
			<xmax>231</xmax>
			<ymax>185</ymax>
		</bndbox>
	</object>
	<object>
		<name>B</name>
		<pose>Unspecified</pose>
		<truncated>0</truncated>
		<difficult>0</difficult>
		<bndbox>
			<xmin>208</xmin>
			<ymin>217</ymin>
			<xmax>217</xmax>
			<ymax>227</ymax>
		</bndbox>
	</object>
	<object>
		<name>NV</name>
		<pose>Unspecified</pose>
		<truncated>0</truncated>
		<difficult>0</difficult>
		<bndbox>
			<xmin>212</xmin>
			<ymin>182</ymin>
			<xmax>228</xmax>
			<ymax>202</ymax>
		</bndbox>
	</object>
	<object>
		<name>H</name>
		<pose>Unspecified</pose>
		<truncated>0</truncated>
		<difficult>0</difficult>
		<bndbox>
			<xmin>152</xmin>
			<ymin>185</ymin>
			<xmax>174</xmax>
			<ymax>209</ymax>
		</bndbox>
	</object>
	<object>
		<name>NV</name>
		<pose>Unspecified</pose>
		<truncated>0</truncated>
		<difficult>0</difficult>
		<bndbox>
			<xmin>138</xmin>
			<ymin>203</ymin>
			<xmax>174</xmax>
			<ymax>243</ymax>
		</bndbox>
	</object>
	<object>
		<name>B</name>
		<pose>Unspecified</pose>
		<truncated>0</truncated>
		<difficult>0</difficult>
		<bndbox>
			<xmin>166</xmin>
			<ymin>268</ymin>
			<xmax>183</xmax>
			<ymax>279</ymax>
		</bndbox>
	</object>
	<object>
		<name>NS</name>
		<pose>Unspecified</pose>
		<truncated>0</truncated>
		<difficult>0</difficult>
		<bndbox>
			<xmin>211</xmin>
			<ymin>182</ymin>
			<xmax>231</xmax>
			<ymax>219</ymax>
		</bndbox>
	</object>
</annotation>
