<annotation>
	<folder>Esam</folder>
	<filename>hard_hat_workers4894.png</filename>
	<path>F:\HardHat_images\Esam\hard_hat_workers4894.png</path>
	<source>
		<database>Unknown</database>
	</source>
	<size>
		<width>416</width>
		<height>416</height>
		<depth>3</depth>
	</size>
	<segmented>0</segmented>
	<object>
		<name>NV</name>
		<pose>Unspecified</pose>
		<truncated>0</truncated>
		<difficult>0</difficult>
		<bndbox>
			<xmin>0</xmin>
			<ymin>358</ymin>
			<xmax>13</xmax>
			<ymax>392</ymax>
		</bndbox>
	</object>
	<object>
		<name>S</name>
		<pose>Unspecified</pose>
		<truncated>0</truncated>
		<difficult>0</difficult>
		<bndbox>
			<xmin>175</xmin>
			<ymin>366</ymin>
			<xmax>214</xmax>
			<ymax>416</ymax>
		</bndbox>
	</object>
	<object>
		<name>H</name>
		<pose>Unspecified</pose>
		<truncated>0</truncated>
		<difficult>0</difficult>
		<bndbox>
			<xmin>2</xmin>
			<ymin>352</ymin>
			<xmax>13</xmax>
			<ymax>366</ymax>
		</bndbox>
	</object>
	<object>
		<name>H</name>
		<pose>Unspecified</pose>
		<truncated>0</truncated>
		<difficult>0</difficult>
		<bndbox>
			<xmin>111</xmin>
			<ymin>352</ymin>
			<xmax>123</xmax>
			<ymax>366</ymax>
		</bndbox>
	</object>
	<object>
		<name>NV</name>
		<pose>Unspecified</pose>
		<truncated>0</truncated>
		<difficult>0</difficult>
		<bndbox>
			<xmin>213</xmin>
			<ymin>97</ymin>
			<xmax>227</xmax>
			<ymax>120</ymax>
		</bndbox>
	</object>
	<object>
		<name>NV</name>
		<pose>Unspecified</pose>
		<truncated>0</truncated>
		<difficult>0</difficult>
		<bndbox>
			<xmin>110</xmin>
			<ymin>363</ymin>
			<xmax>129</xmax>
			<ymax>391</ymax>
		</bndbox>
	</object>
	<object>
		<name>H</name>
		<pose>Unspecified</pose>
		<truncated>0</truncated>
		<difficult>0</difficult>
		<bndbox>
			<xmin>214</xmin>
			<ymin>93</ymin>
			<xmax>224</xmax>
			<ymax>105</ymax>
		</bndbox>
	</object>
	<object>
		<name>H</name>
		<pose>Unspecified</pose>
		<truncated>0</truncated>
		<difficult>0</difficult>
		<bndbox>
			<xmin>182</xmin>
			<ymin>342</ymin>
			<xmax>203</xmax>
			<ymax>368</ymax>
		</bndbox>
	</object>
	<object>
		<name>NV</name>
		<pose>Unspecified</pose>
		<truncated>0</truncated>
		<difficult>0</difficult>
		<bndbox>
			<xmin>175</xmin>
			<ymin>367</ymin>
			<xmax>214</xmax>
			<ymax>416</ymax>
		</bndbox>
	</object>
</annotation>
